kg_lib/__init__.py
kg_lib/fix_pyfzf/__init__.py
kg_lib/fix_pyfzf/pyfzf.py
kg_lib-0.0.3.dist-info/METADATA
kg_lib-0.0.3.dist-info/WHEEL
kg_lib-0.0.3.dist-info/entry_points.txt
kg_lib-0.0.3.dist-info/top_level.txt
kg_lib-0.0.3.dist-info/RECORD
